{"cameraMode":{"drawMode":0,"name":"Shaded","section":"Shading Mode"},"sceneLighting":false,"audioPlay":false,"sceneViewState":{"m_AlwaysRefresh":false,"showFog":true,"showSkybox":false,"showFlares":true,"showImageEffects":true,"showParticleSystems":true,"showVisualEffectGraphs":true,"m_FxEnabled":true},"in2DMode":false,"pivot":{"x":-0.25868818163871767,"y":0.1847335547208786,"z":0.6489998698234558},"rotation":{"x":0.032152965664863589,"y":0.9570625424385071,"z":-0.1168586015701294,"w":0.2633301317691803},"size":0.2635490894317627,"orthographic":false}